MANIFEST.in
README.rst
setup.py
velvet/__init__.py
velvet/cpmmod.py
velvet/sigproc.py
velvet/validation.py
velvet/version.py
velvet.egg-info/PKG-INFO
velvet.egg-info/SOURCES.txt
velvet.egg-info/dependency_links.txt
velvet.egg-info/top_level.txt
velvet/test/__init__.py
velvet/test/test_cpmmod.py
velvet/test/test_sigproc.py