Metadata-Version: 1.1
Name: velvet
Version: 0.0.2
Summary: Beautiful signal processing and communications algorithms in Python
Home-page: https://github.com/sgwoodjr/velvet
Author: SGW
Author-email: sgwoodjr@gmail.com
License: LICENSE
Keywords: signal processing,communications,DSP
Platform: UNKNOWN
Classifier: Development Status :: 1 - Planning
Classifier: Intended Audience :: Science/Research
Classifier: Operating System :: OS Independent
Classifier: Programming Language :: Python
Classifier: Programming Language :: Python :: 2.7
Classifier: Programming Language :: Python :: 3
Classifier: Programming Language :: Python :: Implementation
Classifier: Topic :: Software Development
Classifier: Topic :: Software Development :: Libraries
Classifier: Topic :: Scientific/Engineering
